dimep/__init__.py
dimep/api.py
dimep/tools.py
dimep/version.py
dimep/algo/__init__.py
dimep/algo/bawa.py
dimep/algo/bradnam.py
dimep/algo/chen.py
dimep/algo/guggenberger.py
dimep/algo/lewis.py
dimep/algo/loyda.py
dimep/algo/odergren.py
dimep/algo/rotenberg.py
dimep/algo/summers.py
dimep/algo/wassermann.py
dimep/algo/zewdie.py
dimep/algo/ziemann.py
dimep-0.2.dist-info/METADATA
dimep-0.2.dist-info/WHEEL
dimep-0.2.dist-info/top_level.txt
dimep-0.2.dist-info/RECORD
