Metadata-Version: 2.1
Name: dimep
Version: 0.2
Summary: Measures ipsilateral MEPs
Home-page: https://github.com/translationalneurosurgery/tool-dimep
Author: Robert Guggenberger
Author-email: robert.guggenberger@uni-tuebingen.de
License: MIT
Download-URL: https://github.com/translationalneurosurgery/tool-dimep
Platform: UNKNOWN
Classifier: Development Status :: 5 - Production/Stable
Classifier: Intended Audience :: Science/Research
Classifier: License :: OSI Approved :: MIT License
Classifier: Operating System :: OS Independent
Classifier: Programming Language :: Python :: 3
Classifier: Topic :: Scientific/Engineering
Requires-Dist: scipy
Requires-Dist: numpy
